pytest_snapci/__init__.py
pytest_snapci/plugin.py
pytest_snapci-0.1.4.dist-info/DESCRIPTION.rst
pytest_snapci-0.1.4.dist-info/METADATA
pytest_snapci-0.1.4.dist-info/RECORD
pytest_snapci-0.1.4.dist-info/WHEEL
pytest_snapci-0.1.4.dist-info/entry_points.txt
pytest_snapci-0.1.4.dist-info/metadata.json
pytest_snapci-0.1.4.dist-info/top_level.txt
