Metadata-Version: 2.0
Name: pytest-snapci
Version: 0.1.4
Summary: py.test plugin for Snap-CI
Home-page: https://github.com/thedrow/pytest-snapci
Author: Omer Katz
Author-email: omer.drow@gmail.com
License: UNKNOWN
Platform: UNKNOWN
Classifier: License :: OSI Approved :: MIT License
Classifier: Programming Language :: Python :: 2
